es_logger/__init__.py
es_logger/config.py
es_logger/handler.py
es_logger/setup.py
logship_client-0.1.1.dist-info/METADATA
logship_client-0.1.1.dist-info/WHEEL
logship_client-0.1.1.dist-info/top_level.txt
logship_client-0.1.1.dist-info/RECORD
