Metadata-Version: 2.4
Name: logship-client
Version: 0.1.1
Summary: A unified logging client that ships logs to Elasticsearch with async buffering.
Author-email: AllenFlux <fluxa0223@gmail.com>
License: MIT
Project-URL: Homepage, https://pypi.org/project/logship/
Project-URL: Repository, https://github.com/yourname/logship
Project-URL: Issues, https://github.com/yourname/logship/issues
Keywords: logging,elasticsearch,log,async,python,sdk
Requires-Python: >=3.8
Requires-Dist: requests>=2.32.5
